net/__init__.py
net/hypki/File.py
net/hypki/Ini.py
net/hypki/Logger.py
net/hypki/StringUtils.py
net/hypki/__init__.py
net/hypki/apiutils.py
net/hypki/args.py
net/hypki/asserts.py
net/hypki/io.py
net/hypki/log.py
net/hypki/math.py
net/hypki/random.py
net/hypki/regex.py
net/hypki/system.py
net/hypki/tests/__init__.py
net/hypki/tests/kepler.py
net/hypki/tests/numpytest.py
libs5_python-1.0.11.dist-info/METADATA
libs5_python-1.0.11.dist-info/WHEEL
libs5_python-1.0.11.dist-info/licenses/LICENSE
libs5_python-1.0.11.dist-info/RECORD
