Metadata-Version: 2.4
Name: libs5-python
Version: 1.0.11
Summary: libs5 python scripts, and helper classes (useg e.g. in BEANS software)
Project-URL: Homepage, https://gitlab.com/ahypki/libs5-python
Project-URL: Issues, https://gitlab.com/ahypki/libs5-python/-/issues/
Author: Arkadiusz Hypki
License-Expression: MIT
License-File: LICENSE
Classifier: Operating System :: OS Independent
Classifier: Programming Language :: Python :: 3
Requires-Python: >=3.9
